{
    "list": [
        {
            "value": "62d3fbb0-cd1f-4bd8-808a-ee96acf5572d",
            "key": "工作台考试",
            "exam_time": "2017-09-14 00:00:00"
        },
        {
            "value": "7283ce42-942d-489a-82ec-bdb1efa5d31c",
            "key": "在线考试0914",
            "exam_time": "2017-09-14 00:00:00"
        },
        {
            "value": "91b67ef6-2afb-414c-8f69-160f6b06bdf3",
            "key": "线下考试0914",
            "exam_time": "2017-09-14 00:00:00"
        },
        {
            "value": "a8862140-dea2-4eb8-b73d-ee31701db29f",
            "key": "工作台在线考试0914",
            "exam_time": "2017-09-14 00:00:00"
        },
        {
            "value": "fddafd1e-30ec-4bc0-96bc-e1967d9f8d24",
            "key": "考试",
            "exam_time": "2017-09-14 00:00:00"
        },
        {
            "value": "449c1e76-3772-4b3f-a1d5-b04c092ee304",
            "key": "考试0913",
            "exam_time": "2017-09-13 00:00:00"
        },
        {
            "value": "5f984f42-5bc5-47ad-bef5-4ed8bf1ded0a",
            "key": "在线考试123456",
            "exam_time": "2017-09-08 00:00:00"
        },
        {
            "value": "e2aa41e5-ae81-427e-8b78-be3d0c38108d",
            "key": "在线考试",
            "exam_time": "2017-09-08 00:00:00"
        },
        {
            "value": "e6798f93-968c-47c4-b569-2908bf41730d",
            "key": "考试123",
            "exam_time": "2017-09-08 00:00:00"
        },
        {
            "value": "fff70db3-4553-48b5-a0e2-860e4cc44832",
            "key": "线下考试的测试测试测一",
            "exam_time": "2017-09-06 00:00:00"
        },
        {
            "value": "e12ae42b-6f2a-481e-aa60-bf220c279483",
            "key": "0830测试",
            "exam_time": "2017-08-30 00:00:00"
        },
        {
            "value": "44ff7de3-6a29-4663-87b4-1f7309cfa44f",
            "key": "考试测试",
            "exam_time": "2017-08-17 00:00:00"
        },
        {
            "value": "924042f8-676d-4913-bfba-8f57b82a2076",
            "key": "123456测试",
            "exam_time": "2017-08-17 00:00:00"
        },
        {
            "value": "26d6c3c7-44f9-48a6-bf4d-f0198e95f13c",
            "key": "消息1",
            "exam_time": "2017-08-14 00:00:00"
        },
        {
            "value": "22c48324-a949-46a9-8ed0-5ebcbfddbc27",
            "key": "ceshi3",
            "exam_time": "2017-08-10 00:00:00"
        },
        {
            "value": "df9e0a26-c617-46b5-8479-9d5235f44b6a",
            "key": "测试无反应",
            "exam_time": "2017-08-10 00:00:00"
        },
        {
            "value": "d9c836f1-bb04-4856-b974-da24cb9f1c9c",
            "key": "123",
            "exam_time": "2017-08-09 00:00:00"
        },
        {
            "value": "b619f59c-ddfb-49a5-b9ef-04260b7762c7",
            "key": "考试1",
            "exam_time": "2017-08-07 00:00:00"
        },
        {
            "value": "f26297d8-e635-4c10-a7ff-84215dd58cc9",
            "key": "17测试1",
            "exam_time": "2017-07-18 00:00:00"
        },
        {
            "value": "c3617688-ee8c-42fd-a04d-9c6bc398bb0b",
            "key": "测试提示",
            "exam_time": "2017-03-30 00:00:00"
        },
        {
            "value": "1a361f35-42ab-47e1-bccf-ec646c2e7cc1",
            "key": "手机测试数据",
            "exam_time": "2017-03-20 00:00:00"
        },
        {
            "value": "518c7f0b-2636-491f-8250-2bb608b7b894",
            "key": "手机测试数据2",
            "exam_time": "2017-03-20 00:00:00"
        },
        {
            "value": "1433502f-fccf-4daa-bdd2-e55f7e4df26b",
            "key": "phone1",
            "exam_time": "2017-03-19 00:00:00"
        },
        {
            "value": "23863fa4-d589-43f7-803d-8057bd883054",
            "key": "测试2",
            "exam_time": "2017-03-17 00:00:00"
        },
        {
            "value": "6829a2a3-2950-493b-b683-b493cf599f90",
            "key": "333",
            "exam_time": "2017-03-17 00:00:00"
        },
        {
            "value": "96f4fe0e-a067-4b57-8690-8f11cbdec0ba",
            "key": "44",
            "exam_time": "2017-03-17 00:00:00"
        },
        {
            "value": "dfe75f90-a86c-4d71-a553-20f79b8b6732",
            "key": "测试1",
            "exam_time": "2017-03-17 00:00:00"
        },
        {
            "value": "2a426bd6-de66-4c87-800e-471e05e96c0b",
            "key": "多科测试",
            "exam_time": "2017-03-14 00:00:00"
        },
        {
            "value": "566a1edc-1487-4225-803d-0d8af51c2519",
            "key": "qqq",
            "exam_time": "2017-01-20 00:00:00"
        },
        {
            "value": "586e7bc3-5172-42f2-b32c-c0de105cb18d",
            "key": "h测试2",
            "exam_time": "2017-01-20 00:00:00"
        },
        {
            "value": "6f86ae88-0d50-494a-b298-ccb9ad679247",
            "key": "hbx测试",
            "exam_time": "2017-01-20 00:00:00"
        },
        {
            "value": "8c4b7fab-d70f-43ad-bfd9-045b1587ed72",
            "key": "19测试1",
            "exam_time": "2017-01-19 00:00:00"
        },
        {
            "value": "ac069ae5-5e2b-4933-8d1f-7c832a6648c9",
            "key": "19测试2",
            "exam_time": "2017-01-19 00:00:00"
        },
        {
            "value": "2d57ab2d-4741-48a2-8c1f-6bb73187745c",
            "key": "cs",
            "exam_time": "2017-01-18 00:00:00"
        },
        {
            "value": "5dccb46d-a493-43e7-a7e7-2b0d4a279f31",
            "key": "cs1",
            "exam_time": "2017-01-18 00:00:00"
        },
        {
            "value": "6d4454a0-6c68-486d-9792-633ac3184483",
            "key": "txt2",
            "exam_time": "2017-01-11 00:00:00"
        },
        {
            "value": "baab24b5-5f7c-4d60-acf2-5ceed3f03511",
            "key": "txt1",
            "exam_time": "2017-01-10 00:00:00"
        },
        {
            "value": "5a0a3c66-a421-4bbf-9cb0-8e96018592be",
            "key": "0107",
            "exam_time": "2017-01-07 00:00:00"
        },
        {
            "value": "318b5918-b2cb-47ec-b23b-8bbf45cb7de5",
            "key": "测试专用3",
            "exam_time": "2017-01-03 00:00:00"
        },
        {
            "value": "ae2369da-627e-4297-ac45-381febe5c79b",
            "key": "测试专用5",
            "exam_time": "2017-01-03 00:00:00"
        },
        {
            "value": "ce484026-b1d0-4a34-a2f8-83f715e2d0ff",
            "key": "测试专用1",
            "exam_time": "2017-01-03 00:00:00"
        },
        {
            "value": "eb67c1da-b29f-4681-9a29-cd5e1c92b6ca",
            "key": "考试专用2",
            "exam_time": "2017-01-03 00:00:00"
        },
        {
            "value": "a900e449-a951-4692-a7d5-bb1315d4f189",
            "key": "sql修改测试",
            "exam_time": "2016-12-30 00:00:00"
        },
        {
            "value": "df04d435-1a5d-4d54-99b7-997fdbc63890",
            "key": "显示创建",
            "exam_time": "2016-12-19 00:00:00"
        },
        {
            "value": "367ebc1b-8da8-4bcc-a2d8-ef642e566e6f",
            "key": "手机版测试",
            "exam_time": "2016-12-15 00:00:00"
        },
        {
            "value": "48fe1502-7b0c-4cbe-a4df-57e01c9b4978",
            "key": "pc版测试",
            "exam_time": "2016-12-15 00:00:00"
        },
        {
            "value": "823f9501-3829-4f11-b793-040dcbf571f5",
            "key": "txt20161215",
            "exam_time": "2016-12-15 00:00:00"
        },
        {
            "value": "8ab69852-e815-464f-86d3-0252619c1424",
            "key": "数学ces",
            "exam_time": "2016-12-13 00:00:00"
        },
        {
            "value": "1d0017c9-966b-4eb1-bf24-0a7ff5a8a901",
            "key": "全年级考试",
            "exam_time": "2016-11-09 00:00:00"
        },
        {
            "value": "0951c1e4-fc14-4af9-985c-5b4cb1a613f8",
            "key": "离线考试测试",
            "exam_time": "2016-11-04 00:00:00"
        },
        {
            "value": "190e8baa-9e1e-4e07-a55d-14e4bf3385d1",
            "key": "test save",
            "exam_time": "2016-11-02 00:00:00"
        },
        {
            "value": "50eb2e5e-9d2e-4256-ab5b-9fff0ad68fac",
            "key": "tst",
            "exam_time": "2016-10-22 00:00:00"
        },
        {
            "value": "0af44c4c-6baa-4432-9b87-64ca539964cc",
            "key": "考试测试练习",
            "exam_time": "2016-10-17 00:00:00"
        },
        {
            "value": "aaf3dc5b-9a1f-4d9f-977b-006183bac9b6",
            "key": "考试",
            "exam_time": "2016-10-17 00:00:00"
        }
    ]
}
